pvenv/__init__.py
pvenv/__main__.py
pvenv/__version__.py
pvenv/lib/__init__.py
pvenv/lib/cli.py
pvenv/lib/constants.py
pvenv/py.typed
pvenv/scripts/pvenv.sh
pvenv/subcommands/__init__.py
pvenv/subcommands/avenv.py
pvenv/subcommands/base.py
pvenv/subcommands/dvenv.py
pvenv/subcommands/initvenv.py
pvenv/subcommands/invenv.py
pvenv/subcommands/lsvenv.py
pvenv/subcommands/mkvenv.py
pvenv/subcommands/outvenv.py
pvenv/subcommands/rmvenv.py
pvenv-3.2.3.dist-info/LICENSE.md
pvenv-3.2.3.dist-info/METADATA
pvenv-3.2.3.dist-info/WHEEL
pvenv-3.2.3.dist-info/entry_points.txt
pvenv-3.2.3.dist-info/RECORD
