Metadata-Version: 2.3
Name: pvenv
Version: 3.2.3
Summary: Easy python virtual environment management
Home-page: https://p-venv.readthedocs.io/en/stable/
License: BSD-3-Clause
Keywords: venv
Author: Stephanos Kuma
Author-email: "Stephanos Kuma" <stephanos@kuma.ai>
Requires-Python: >=3.9
Classifier: Development Status :: 5 - Production/Stable
Classifier: Intended Audience :: Developers
Classifier: License :: OSI Approved :: BSD License
Classifier: Operating System :: OS Independent
Classifier: Programming Language :: Python :: 3 :: Only
Classifier: Topic :: Software Development :: User Interfaces
Requires-Dist: dj-settings (~=8.0)
Requires-Dist: pyutilkit (~=0.10)
Requires-Dist: uv (~=0.9)
Project-URL: Documentation, https://p-venv.readthedocs.io/en/stable/
Project-URL: Repository, https://github.com/spapanik/pvenv
